controlmatrix.sv
module control_matrix (
                      input logic clock,
                      input logic [3:0] opcode,
                      input logic branch_flag,
                      input logic [2:0]state,
                      output logic [0:0] alternate_read,
                      output logic [0:0] alt_write,
                      //input logic reset_signals,
                      input logic LT_flag,
                      output logic [1:0] alu_control,
                      output logic [0:0] extender_reset,
                      output logic [0:0] state_machine_reset,
                      /*register enables and resets*/
                      output logic [0:0] PC_EN,
                      output logic [0:0] PC_reset,
                      output logic [0:0] reset_reg_file,
                      output logic [0:0] read_1EN,
                      output logic [0:0] read_2EN,
                      output logic [0:0] reg_file_wrEN,
                      output logic [0:0] EN_mem_add,
                      output logic [0:0] mem_add_reset,
                      output logic [0:0] RAM_wrEN,
                      output logic [0:0] RAM_rddisEN,
                      output logic [0:0] EN_output,
                      output logic [0:0] output_reset,
                      output logic [0:0] ten_branch,
                      output logic [0:0] LT_state,
                      output logic [0:0] PC_or_read_mem,
                      output logic [0:0] PC_in_op,
                      output logic [0:0] lineb_ex,
                      output logic [0:0] alu_linea,
                      output logic [0:0] Altsel,
                      output logic [0:0] Altwrsel
                      );
            reg less_than_flag; //LT_flag_set gets this.
            reg [3:0] opcode_store;
            logic control_reset;
always @ (*) begin
  ten_branch <= branch_flag;
  LT_state <= less_than_flag;
  if (state == 0) begin
    PC_EN <= 1;
    opcode_store = opcode;
    end
  if (state == 1)
    PC_EN <= 0;
  if (state == 6)
    opcode_store = 4'b1111;
  case (opcode_store)
  4'b0001: begin PC_in_op <= 1; /*JMP absolute jump*/
        end
  4'b0010: begin /*LDW load bitstring from memory to register*/
            if (state == 1) begin
            alu_control <= 2'b00;
            alternate_read <= 16'd2;//line going to A alternate_read <= 16'd2;
            Altsel <= 1;            //control going to A mux alt_orA
            read_1EN <= 1;
            PC_or_read_mem <= 1;
            lineb_ex <= 1;
            end
            else if (state == 2) begin
            PC_or_read_mem <= 1;
            alt_write <=16'd1;//line going to write address <= 16'd1;
            Altwrsel <= 1;//flag for alternate write address
            RAM_rddisEN <= 1; //keep ram from reading weird alu results from adding new words
            end
            else if (state == 3) begin
            reg_file_wrEN <= 1;
            end
        end
  4'b0011: begin /*STW store register val in memory*/
        end
  4'b0100: begin /*RTR copy register to register)*/

        end
  4'b0101: begin /*BLT branch if less than*/
          if (state == 1) begin
          alu_control <= 2'b01;
          read_1EN <= 1;
          read_2EN <= 1;
          end
          else if (state == 2) begin
          less_than_flag <= LT_flag;
          read_1EN <= 0;
          read_2EN <= 0;
          end
        end
  4'b0110: begin alu_control <= 00;/*ADD add registers together*/
        end
  4'b0111: begin alu_control <= 01;/*SUB subtract registers from each other*/
      end
  4'b1111: begin
                //input logic reset_signals,
                 alu_control <= 2'b00;
                 extender_reset <= 0;
                 //state_machine_reset <= 0;
                /*register enables and resets*/
                 PC_EN <= 0;
                 PC_reset <= 0;
                 reset_reg_file <= 0;
                 read_1EN <= 0;
                 read_2EN <= 0;
                 reg_file_wrEN <= 0;
                 EN_mem_add <= 0;
                 mem_add_reset <= 0;
                 RAM_wrEN <= 0;
                 RAM_rddisEN <= 0;
                 EN_output <= 0;
                 output_reset <= 0;
                /*mux selects*/
                 ten_branch <= 0;
                 LT_state <= 0; //LT selects whether or not to branc = 0;
                 PC_or_read_mem <= 0;
                 PC_in_op <= 0;
                 lineb_ex <= 0;
                 alu_linea <= 0;
                 less_than_flag <= 0;
                 Altsel <= 0;
                 Altwrsel <= 0;
                 alt_write <= 0;
                 alternate_read <= 0;
                 end

    default: alu_control <= 2'b11;
    endcase
end
endmodule

controlmatrix_tb.sv

timeunit 10ps/1ps;
module test ();
                logic [3:0] opcode;
                logic branch_flag;
                logic [2:0]state;
                logic [0:0] alternate_read;
                logic [0:0] alt_write;
                logic LT_flag;
                logic [1:0] alu_control;
                logic extender_reset;
                logic state_machine_reset;
                logic PC_EN;
                logic PC_reset;
                logic reset_reg_file;
                logic read_1EN;
                logic read_2EN;
                logic reg_file_wrEN;
                logic EN_mem_add;
                logic mem_add_reset;
                logic RAM_wrEN;
                logic RAM_rddisEN;
                logic EN_output;
                logic output_reset;
                logic ten_branch;
                logic LT_state; //LT selects whether or not to branch
                logic PC_or_read_mem;
                logic PC_in_op;
                logic lineb_ex;
                logic alu_linea;
                logic clock;
                logic control_reset;
                logic [0:0] Altsel;
                logic [0:0] Altwrsel;
                reg opcode_store;
      control_matrix u1(.*);
  initial begin
        $dumpfile("control_matrix.vcd");
        $dumpvars;
        control_reset = 1'b1;
        clock = 1;
        state = 0;
  end
  always begin
  #5  clock = !clock;
  end


  initial begin
  #10
  opcode = 4'b1111;
  state = 0;
  #10
  state = 0;
  opcode = 4'b0001;
  #10
  state = 1;
  #10
  state = 2;
  #10
  state = 3;
  #10
  state = 4;
  #10
  state = 5;
  #10
  state = 6;
  #10
  opcode = 4'b0010;
  state = 0;
  #10
  state = 1;
  #10
  state = 2;
  #10
  state = 3;
  #10
  state = 4;
  #10
  state = 5;
  #10
  state = 6;
  #10
  opcode = 4'b0011;
  state = 0;
  #10
  state = 1;
  #10
  state = 2;
  #10
  state = 3;
  #10
  state = 4;
  #10
  state = 5;
  #10
  state = 6;
  #10
  opcode = 4'b0100;
  state = 0;
  #10
  state = 1;
  #10
  state = 2;
  #10
  state = 3;
  #10
  state = 4;
  #10
  state = 5;
  #10
  state = 6;
  #10
  opcode = 4'b0101;
  state = 0;
  #10
  state = 1;
  #10
  state = 2;
  #10
  state = 3;
  #10
  state = 4;
  #10
  state = 5;
  #10
  state = 6;
  #10
  opcode = 4'b0110;
  state = 0;
  #10
  state = 1;
  #10
  state = 2;
  #10
  state = 3;
  #10
  state = 4;
  #10
  state = 5;
  #10
  state = 6;
  #10
  opcode = 4'b0111;
  state = 0;
  #10
  state = 1;
  #10
  state = 2;
  #10
  state = 3;
  #10
  state = 4;
  #10
  state = 5;
  #10
  state = 6;
  #10
  #10
  $finish();
  end
endmodule

control_matrix.vcd
$date
	Fri Jun  8 02:28:22 2018
$end
$version
	Icarus Verilog
$end
$timescale
	1ps
$end
$scope module test $end
$var wire 1 ! ten_branch $end
$var wire 1 " state_machine_reset $end
$var wire 1 # reset_reg_file $end
$var wire 1 $ reg_file_wrEN $end
$var wire 1 % read_2EN $end
$var wire 1 & read_1EN $end
$var wire 1 ' output_reset $end
$var wire 1 ( mem_add_reset $end
$var wire 1 ) lineb_ex $end
$var wire 1 * extender_reset $end
$var wire 1 + alu_linea $end
$var wire 2 , alu_control [1:0] $end
$var wire 1 - alternate_read $end
$var wire 1 . alt_write $end
$var wire 1 / RAM_wrEN $end
$var wire 1 0 RAM_rddisEN $end
$var wire 1 1 PC_reset $end
$var wire 1 2 PC_or_read_mem $end
$var wire 1 3 PC_in_op $end
$var wire 1 4 PC_EN $end
$var wire 1 5 LT_state $end
$var wire 1 6 EN_output $end
$var wire 1 7 EN_mem_add $end
$var wire 1 8 Altwrsel $end
$var wire 1 9 Altsel $end
$var reg 1 : LT_flag $end
$var reg 1 ; branch_flag $end
$var reg 1 < clock $end
$var reg 1 = control_reset $end
$var reg 4 > opcode [3:0] $end
$var reg 3 ? state [2:0] $end
$scope module u1 $end
$var wire 1 : LT_flag $end
$var wire 1 ; branch_flag $end
$var wire 1 < clock $end
$var wire 4 @ opcode [3:0] $end
$var wire 3 A state [2:0] $end
$var reg 1 9 Altsel $end
$var reg 1 8 Altwrsel $end
$var reg 1 7 EN_mem_add $end
$var reg 1 6 EN_output $end
$var reg 1 5 LT_state $end
$var reg 1 4 PC_EN $end
$var reg 1 3 PC_in_op $end
$var reg 1 2 PC_or_read_mem $end
$var reg 1 1 PC_reset $end
$var reg 1 0 RAM_rddisEN $end
$var reg 1 / RAM_wrEN $end
$var reg 1 . alt_write $end
$var reg 1 - alternate_read $end
$var reg 2 B alu_control [1:0] $end
$var reg 1 + alu_linea $end
$var reg 1 * extender_reset $end
$var reg 1 C less_than_flag $end
$var reg 1 ) lineb_ex $end
$var reg 1 ( mem_add_reset $end
$var reg 4 D opcode_store [3:0] $end
$var reg 1 ' output_reset $end
$var reg 1 & read_1EN $end
$var reg 1 % read_2EN $end
$var reg 1 $ reg_file_wrEN $end
$var reg 1 # reset_reg_file $end
$var reg 1 " state_machine_reset $end
$var reg 1 ! ten_branch $end
$upscope $end
$upscope $end
$enddefinitions $end
#0
$dumpvars
bx D
xC
b11 B
b0 A
bx @
b0 ?
bx >
1=
1<
x;
x:
x9
x8
x7
x6
x5
14
x3
x2
x1
x0
x/
x.
x-
b11 ,
x+
x*
x)
x(
x'
x&
x%
x$
x#
x"
x!
$end
#50
0<
#100
0-
0.
08
09
0C
0+
0)
03
02
05
0!
0'
06
00
0/
0(
07
0$
0%
0&
0#
01
04
0*
b0 ,
b0 B
b1111 D
1<
b1111 >
b1111 @
#150
0<
#200
13
14
x!
b1 D
1<
b1 >
b1 @
#250
0<
#300
04
1<
b1 ?
b1 A
#350
0<
#400
1<
b10 ?
b10 A
#450
0<
#500
1<
b11 ?
b11 A
#550
0<
#600
1<
b100 ?
b100 A
#650
0<
#700
1<
b101 ?
b101 A
#750
0<
#800
03
0!
b1111 D
1<
b110 ?
b110 A
#850
0<
#900
14
x!
b10 D
1<
b0 ?
b0 A
b10 >
b10 @
#950
0<
#1000
1)
12
1&
19
04
1<
b1 ?
b1 A
#1050
0<
#1100
10
18
1.
1<
b10 ?
b10 A
#1150
0<
#1200
1$
1<
b11 ?
b11 A
#1250
0<
#1300
1<
b100 ?
b100 A
#1350
0<
#1400
1<
b101 ?
b101 A
#1450
0<
#1500
0.
08
09
0)
02
0!
00
0$
0&
b1111 D
1<
b110 ?
b110 A
#1550
0<
#1600
14
x!
b11 D
1<
b0 ?
b0 A
b11 >
b11 @
#1650
0<
#1700
04
1<
b1 ?
b1 A
#1750
0<
#1800
1<
b10 ?
b10 A
#1850
0<
#1900
1<
b11 ?
b11 A
#1950
0<
#2000
1<
b100 ?
b100 A
#2050
0<
#2100
1<
b101 ?
b101 A
#2150
0<
#2200
0!
b1111 D
1<
b110 ?
b110 A
#2250
0<
#2300
14
x!
b100 D
1<
b0 ?
b0 A
b100 >
b100 @
#2350
0<
#2400
04
1<
b1 ?
b1 A
#2450
0<
#2500
1<
b10 ?
b10 A
#2550
0<
#2600
1<
b11 ?
b11 A
#2650
0<
#2700
1<
b100 ?
b100 A
#2750
0<
#2800
1<
b101 ?
b101 A
#2850
0<
#2900
0!
b1111 D
1<
b110 ?
b110 A
#2950
0<
#3000
14
x!
b101 D
1<
b0 ?
b0 A
b101 >
b101 @
#3050
0<
#3100
1%
1&
b1 ,
b1 B
04
1<
b1 ?
b1 A
#3150
0<
#3200
x5
0%
0&
xC
1<
b10 ?
b10 A
#3250
0<
#3300
1<
b11 ?
b11 A
#3350
0<
#3400
1<
b100 ?
b100 A
#3450
0<
#3500
1<
b101 ?
b101 A
#3550
0<
#3600
0C
05
0!
b0 ,
b0 B
b1111 D
1<
b110 ?
b110 A
#3650
0<
#3700
14
x!
b110 D
1<
b0 ?
b0 A
b110 >
b110 @
#3750
0<
#3800
04
1<
b1 ?
b1 A
#3850
0<
#3900
1<
b10 ?
b10 A
#3950
0<
#4000
1<
b11 ?
b11 A
#4050
0<
#4100
1<
b100 ?
b100 A
#4150
0<
#4200
1<
b101 ?
b101 A
#4250
0<
#4300
0!
b1111 D
1<
b110 ?
b110 A
#4350
0<
#4400
b1 ,
b1 B
14
x!
b111 D
1<
b0 ?
b0 A
b111 >
b111 @
#4450
0<
#4500
04
1<
b1 ?
b1 A
#4550
0<
#4600
1<
b10 ?
b10 A
#4650
0<
#4700
1<
b11 ?
b11 A
#4750
0<
#4800
1<
b100 ?
b100 A
#4850
0<
#4900
1<
b101 ?
b101 A
#4950
0<
#5000
0!
b0 ,
b0 B
b1111 D
1<
b110 ?
b110 A
