controlmatrix.sv
module control_matrix (
                      input logic clock,
                      input logic [3:0] opcode,
                      input logic branch_flag,
                      input logic [1:0]state,
                      output logic [4:0] alternate_read,
                      output logic [4:0] alt_write,
                      //input logic reset_signals,
                      input logic LT_flag,
                      output logic [1:0] alu_control,
                      output logic [0:0] extender_reset,
                      output logic [0:0] state_machine_reset,
                      /*register enables and resets*/
                      output logic [0:0] PC_EN,
                      output logic [0:0] PC_reset,
                      output logic [0:0] reset_reg_file,
                      output logic [0:0] read_1EN,
                      output logic [0:0] read_2EN,
                      output logic [0:0] reg_file_wrEN,
                      output logic [0:0] EN_mem_add,
                      output logic [0:0] mem_add_reset,
                      output logic [0:0] RAM_wrEN,
                      output logic [0:0] RAM_rddisEN,
                      output logic [0:0] EN_output,
                      output logic [0:0] output_reset,
                      output logic [0:0] ten_branch,
                      output logic [0:0] LT_state,
                      output logic [0:0] PC_or_read_mem,
                      output logic [0:0] PC_in_op,
                      output logic [0:0] lineb_ex,
                      output logic [0:0] alu_linea,
                      output logic [0:0] Altsel,
                      output logic [0:0] Altwrsel
                      );
            reg less_than_flag; //LT_flag_set gets this.
            reg [3:0] opcode_store;
            logic control_reset;
always @ (*) begin
  ten_branch <= branch_flag;
  LT_state <= less_than_flag;
  if (state == 0) begin //flushes the state of the machine
     alu_control <= 2'b00;
     extender_reset <= 0;
     PC_EN <= 0;
     PC_reset <= 0;
     reset_reg_file <= 0;
     read_1EN <= 0;
     read_2EN <= 0;
     reg_file_wrEN <= 0;
     EN_mem_add <= 0;
     mem_add_reset <= 0;
     RAM_wrEN <= 0;
     RAM_rddisEN <= 0;
     EN_output <= 0;
     output_reset <= 0;
     ten_branch <= 0;
     LT_state <= 0;
     PC_or_read_mem <= 0;
     PC_in_op <= 0;
     lineb_ex <= 0;
     alu_linea <= 0;
     less_than_flag <= 0;
     Altsel <= 0;
     Altwrsel <= 0;
     alt_write <= 0;
     alternate_read <= 0;
     //changes PC and gets op code
     PC_EN <= 1;
     opcode_store = opcode;
     end
  else if (state == 1) begin
    PC_EN <= 0;
    //prep incase of a reset
    mem_add_reset <= 1;
    output_reset <= 1;
    end
  case (opcode_store)
  4'b0000: begin //update output
            if (state == 1) begin
              read_1EN <= 1;
              Altsel <= 1;
              alternate_read <= 4'd4;
              EN_output <= 1;
              end
          end
  4'b0001: begin PC_in_op <= 1; /*JMP absolute jump*/
        end
  4'b0010: begin /*LDW load bitstring from memory to register*/
            if (state == 1) begin
              Altsel <= 1;            //control going to A mux alt_orA
              alternate_read <= 4'd2;//line going to A alternate_read 16'd2 has memory offset
              read_1EN <= 1;
              PC_or_read_mem <= 1;
              lineb_ex <= 1;
            end
            else if (state == 2) begin
              PC_or_read_mem <= 1;
              alt_write <= 4'd1;//line going to write address <= 16'd1;
              Altwrsel <= 1;//flag for alternate write address
              RAM_rddisEN <= 1; //keep ram from reading weird alu results from adding new words
            end
            else if (state == 3) begin
              reg_file_wrEN <= 1;
            end
        end
  4'b0011: begin /*STW store register val in memory*/
            if (state == 1) begin
              Altsel <= 1;
              alternate_read <= 4'd2;
              read_1EN <= 1;
              lineb_ex <= 1;
            end
            else if (state == 2) begin
            EN_mem_add <= 1;
            end
            else if (state == 3) begin
            EN_mem_add <= 0;
              alternate_read <= 4'd3; //d3 is where registers are copied to for storeage
              alu_linea <= 1;
              RAM_wrEN <= 1;
            end

        end
  4'b0100: begin /*RTR copy register to register)*/
          if (state == 1) begin
            read_2EN <= 1;
            Altsel <= 1;
            alternate_read <= 0;
          end
          if (state == 2) begin
            reg_file_wrEN <= 1;
          end
        end
  4'b0101: begin /*BLT branch if less than*/
          if (state == 1) begin
            alu_control <= 2'b01;
            read_1EN <= 1;
            read_2EN <= 1;
          end
          else if (state == 2) begin
            LT_state <= less_than_flag;
          end
          else if (state == 2) begin
            ten_branch <= branch_flag; //if branch_flag is 0, the branch is -10.  10 if 1.
          end
        end
  4'b0110: begin alu_control <= 00;/*ADD add registers together*/
            if (state == 1) begin
              read_1EN <= 1;
              read_2EN <= 1;
            end
            else if (state == 2) begin
              Altwrsel <= 1;
              alt_write <= 4'd4;
              reg_file_wrEN <= 1;
            end
            else if (state == 3) begin
              reg_file_wrEN <= 0;
            end
        end
  4'b0111: begin alu_control <= 01;/*SUB subtract registers from each other*/
            if (state == 1) begin
              read_1EN <= 1;
              read_2EN <= 1;
            end
            else if (state == 2) begin
              Altwrsel <= 1;
              alt_write <= 4'd4;
              reg_file_wrEN <= 1;
            end
            else if (state == 3) begin
              reg_file_wrEN <= 0;
            end
        end
  default: begin
                //input logic reset_signals,
                 alu_control <= 2'b00;
                 extender_reset <= 0;
                 //state_machine_reset <= 0;
                /*register enables and resets*/
                 PC_EN <= 0;
                 PC_reset <= 0;
                 reset_reg_file <= 0;
                 read_1EN <= 0;
                 read_2EN <= 0;
                 reg_file_wrEN <= 0;
                 EN_mem_add <= 0;
                 mem_add_reset <= 0;
                 RAM_wrEN <= 0;
                 RAM_rddisEN <= 0;
                 EN_output <= 0;
                 output_reset <= 0;
                /*mux selects*/
                 ten_branch <= 0;
                 LT_state <= 0; //LT selects whether or not to branc = 0;
                 PC_or_read_mem <= 0;
                 PC_in_op <= 0;
                 lineb_ex <= 0;
                 alu_linea <= 0;
                 less_than_flag <= 0;
                 Altsel <= 0;
                 Altwrsel <= 0;
                 alt_write <= 0;
                 alternate_read <= 0;
                 end
    endcase
end
endmodule

controlmatrix_tb.sv
timeunit 10ps/1ps;
module test ();
                logic [3:0] opcode;
                logic branch_flag;
                logic [1:0]state;
                logic [4:0] alternate_read;
                logic [4:0] alt_write;
                logic LT_flag;
                logic [1:0] alu_control;
                logic extender_reset;
                logic state_machine_reset;
                logic PC_EN;
                logic PC_reset;
                logic reset_reg_file;
                logic read_1EN;
                logic read_2EN;
                logic reg_file_wrEN;
                logic EN_mem_add;
                logic mem_add_reset;
                logic RAM_wrEN;
                logic RAM_rddisEN;
                logic EN_output;
                logic output_reset;
                logic ten_branch;
                logic LT_state; //LT selects whether or not to branch
                logic PC_or_read_mem;
                logic PC_in_op;
                logic lineb_ex;
                logic alu_linea;
                logic clock;
                logic control_reset;
                logic [0:0] Altsel;
                logic [0:0] Altwrsel;
                reg opcode_store;
      control_matrix u1(.*);
  initial begin
        $dumpfile("control_matrix.vcd");
        $dumpvars;
        control_reset = 1'b1;
        clock = 1;
        state = 0;
  end
  always begin
  #5  clock = !clock;
  end


  initial begin
  #10
  opcode = 4'b1111;
  state = 0;
  #10
  opcode = 4'b0001;
  state = 0;
  #10
  state = 1;
  #10
  state = 2;
  #10
  state = 3;
  #10
  opcode = 4'b0001;
  state = 0;
  #10
  state = 1;
  #10
  state = 2;
  #10
  state = 3;
  #10
  opcode = 4'b0010;
  state = 0;
  #10
  state = 1;
  #10
  state = 2;
  #10
  state = 3;
  #10
  opcode = 4'b0011;
  state = 0;
  #10
  state = 1;
  #10
  state = 2;
  #10
  state = 3;
  #10
  opcode = 4'b0100;
  state = 0;
  #10
  state = 1;
  #10
  state = 2;
  #10
  state = 3;
  #10
  opcode = 4'b0101;
  state = 0;
  #10
  state = 1;
  #10
  state = 2;
  #10
  state = 3;
  #10
  opcode = 4'b0110;
  state = 0;
  #10
  state = 1;
  #10
  state = 2;
  #10
  state = 3;
  #10
  opcode = 4'b0111;
  state = 0;
  #10
  state = 1;
  #10
  state = 2;
  #10
  state = 3;
  #10
  #10
  $finish();
  end
endmodule

control_matrix.vcd
$date
	Fri Jun  8 03:59:01 2018
$end
$version
	Icarus Verilog
$end
$timescale
	1ps
$end
$scope module test $end
$var wire 1 ! ten_branch $end
$var wire 1 " state_machine_reset $end
$var wire 1 # reset_reg_file $end
$var wire 1 $ reg_file_wrEN $end
$var wire 1 % read_2EN $end
$var wire 1 & read_1EN $end
$var wire 1 ' output_reset $end
$var wire 1 ( mem_add_reset $end
$var wire 1 ) lineb_ex $end
$var wire 1 * extender_reset $end
$var wire 1 + alu_linea $end
$var wire 2 , alu_control [1:0] $end
$var wire 5 - alternate_read [4:0] $end
$var wire 5 . alt_write [4:0] $end
$var wire 1 / RAM_wrEN $end
$var wire 1 0 RAM_rddisEN $end
$var wire 1 1 PC_reset $end
$var wire 1 2 PC_or_read_mem $end
$var wire 1 3 PC_in_op $end
$var wire 1 4 PC_EN $end
$var wire 1 5 LT_state $end
$var wire 1 6 EN_output $end
$var wire 1 7 EN_mem_add $end
$var wire 1 8 Altwrsel $end
$var wire 1 9 Altsel $end
$var reg 1 : LT_flag $end
$var reg 1 ; branch_flag $end
$var reg 1 < clock $end
$var reg 1 = control_reset $end
$var reg 4 > opcode [3:0] $end
$var reg 2 ? state [1:0] $end
$scope module u1 $end
$var wire 1 : LT_flag $end
$var wire 1 ; branch_flag $end
$var wire 1 < clock $end
$var wire 4 @ opcode [3:0] $end
$var wire 2 A state [1:0] $end
$var reg 1 9 Altsel $end
$var reg 1 8 Altwrsel $end
$var reg 1 7 EN_mem_add $end
$var reg 1 6 EN_output $end
$var reg 1 5 LT_state $end
$var reg 1 4 PC_EN $end
$var reg 1 3 PC_in_op $end
$var reg 1 2 PC_or_read_mem $end
$var reg 1 1 PC_reset $end
$var reg 1 0 RAM_rddisEN $end
$var reg 1 / RAM_wrEN $end
$var reg 5 B alt_write [4:0] $end
$var reg 5 C alternate_read [4:0] $end
$var reg 2 D alu_control [1:0] $end
$var reg 1 + alu_linea $end
$var reg 1 * extender_reset $end
$var reg 1 E less_than_flag $end
$var reg 1 ) lineb_ex $end
$var reg 1 ( mem_add_reset $end
$var reg 4 F opcode_store [3:0] $end
$var reg 1 ' output_reset $end
$var reg 1 & read_1EN $end
$var reg 1 % read_2EN $end
$var reg 1 $ reg_file_wrEN $end
$var reg 1 # reset_reg_file $end
$var reg 1 " state_machine_reset $end
$var reg 1 ! ten_branch $end
$upscope $end
$upscope $end
$enddefinitions $end
#0
$dumpvars
bx F
0E
b0 D
b0 C
b0 B
b0 A
bx @
b0 ?
bx >
1=
1<
x;
x:
09
08
07
06
05
04
03
02
01
00
0/
b0 .
b0 -
b0 ,
0+
0*
0)
0(
0'
0&
0%
0$
0#
x"
0!
$end
#50
0<
#100
04
0!
b1111 F
1<
b1111 >
b1111 @
#150
0<
#200
13
14
0!
b1 F
1<
b1 >
b1 @
#250
0<
#300
04
x!
1<
b1 ?
b1 A
#350
0<
#400
1<
b10 ?
b10 A
#450
0<
#500
1<
b11 ?
b11 A
#550
0<
#600
14
13
0!
1<
b0 ?
b0 A
#650
0<
#700
04
x!
1<
b1 ?
b1 A
#750
0<
#800
1<
b10 ?
b10 A
#850
0<
#900
1<
b11 ?
b11 A
#950
0<
#1000
14
03
0!
b10 F
1<
b0 ?
b0 A
b10 >
b10 @
#1050
0<
#1100
1)
12
1&
b10 -
b10 C
19
04
x!
1<
b1 ?
b1 A
#1150
0<
#1200
10
18
b1 .
b1 B
1<
b10 ?
b10 A
#1250
0<
#1300
1$
1<
b11 ?
b11 A
#1350
0<
#1400
14
b0 -
b0 C
b0 .
b0 B
08
09
0)
02
0!
00
0$
0&
b11 F
1<
b0 ?
b0 A
b11 >
b11 @
#1450
0<
#1500
1)
1&
b10 -
b10 C
19
04
x!
1<
b1 ?
b1 A
#1550
0<
#1600
17
1<
b10 ?
b10 A
#1650
0<
#1700
1/
1+
b11 -
b11 C
07
1<
b11 ?
b11 A
#1750
0<
#1800
14
b0 -
b0 C
09
0+
0)
0!
0/
0&
b100 F
1<
b0 ?
b0 A
b100 >
b100 @
#1850
0<
#1900
19
1%
04
x!
1<
b1 ?
b1 A
#1950
0<
#2000
1$
1<
b10 ?
b10 A
#2050
0<
#2100
1<
b11 ?
b11 A
#2150
0<
#2200
14
09
0!
0$
0%
b101 F
1<
b0 ?
b0 A
b101 >
b101 @
#2250
0<
#2300
1%
1&
b1 ,
b1 D
04
x!
1<
b1 ?
b1 A
#2350
0<
#2400
1<
b10 ?
b10 A
#2450
0<
#2500
1<
b11 ?
b11 A
#2550
0<
#2600
14
0!
0%
0&
b0 ,
b0 D
b110 F
1<
b0 ?
b0 A
b110 >
b110 @
#2650
0<
#2700
1%
1&
04
x!
1<
b1 ?
b1 A
#2750
0<
#2800
1$
b100 .
b100 B
18
1<
b10 ?
b10 A
#2850
0<
#2900
0$
1<
b11 ?
b11 A
#2950
0<
#3000
b1 ,
b1 D
14
b0 .
b0 B
08
0!
0%
0&
b111 F
1<
b0 ?
b0 A
b111 >
b111 @
#3050
0<
#3100
1%
1&
04
x!
1<
b1 ?
b1 A
#3150
0<
#3200
1$
b100 .
b100 B
18
1<
b10 ?
b10 A
#3250
0<
#3300
0$
1<
b11 ?
b11 A
