mux4.sv
module multiplexer4 #(parameter bus_size = 15)
                      (input logic [1:0] select,
                      input logic [bus_size:0] line_1,
                      input logic [bus_size:0] line_2,
                      input logic [bus_size:0] line_3,
                      input logic [bus_size:0] line_4,
                      output logic [bus_size:0] out);
always @ *
begin
  case (select)
  2'b00: out = line_1;
  2'b01: out = line_2;
  2'b10: out = line_3;
  2'b11: out = line_4;
  endcase
end
endmodule

mux4_tb.sv
timeunit 10ps/1ps;
module test ();
      logic [1:0] select;
    	logic [15:0] line_1;
    	logic [15:0] line_2;
    	logic [15:0] line_3;
    	logic [15:0] line_4;
    	logic [15:0] out;
      multiplexer4 u1(.*);
  initial begin
        $dumpfile("mux4.vcd");
        $dumpvars;
  select = 2'b00;
  line_1 = 16'd10;
  line_2 = 16'd20;
  line_3 = 16'd20;
  line_4 = 16'd20;
  end

  initial begin
    #10;
  line_1 = 16'd30;
    #10;
  line_1 = 16'd20;
  line_2 = 16'd10;
  line_3 = 16'd40;
  line_4 = 16'd50;
    #10;
  select = 2'b01;
    #10;
  line_1 = 16'd20;
  line_2 = 16'd10;
  line_3 = 16'd40;
  line_4 = 16'd50;
    #10;
  select = 2'b10;
  line_3 = 16'd50;
    #10;
  line_1 = 16'd00;
  line_2 = 16'd00;
  line_3 = 16'd20;
  line_4 = 16'd00;
    #10;
  select = 2'b11;
    #10;
  line_4 = 16'd50;
    #10;
  line_1 = 16'd20;
  line_2 = 16'd10;
  line_3 = 16'd40;
  line_4 = 16'd50;
  $finish();
  end
endmodule

mux4.vcd
$date
	Mon Jun  4 12:55:45 2018
$end
$version
	Icarus Verilog
$end
$timescale
	1ps
$end
$scope module test $end
$var wire 16 ! out [15:0] $end
$var reg 16 " line_1 [15:0] $end
$var reg 16 # line_2 [15:0] $end
$var reg 16 $ line_3 [15:0] $end
$var reg 16 % line_4 [15:0] $end
$var reg 2 & select [1:0] $end
$scope module u1 $end
$var wire 16 ' line_1 [15:0] $end
$var wire 16 ( line_2 [15:0] $end
$var wire 16 ) line_3 [15:0] $end
$var wire 16 * line_4 [15:0] $end
$var wire 2 + select [1:0] $end
$var reg 16 , out [15:0] $end
$upscope $end
$upscope $end
$enddefinitions $end
#0
$dumpvars
b1010 ,
b0 +
b10100 *
b10100 )
b10100 (
b1010 '
b0 &
b10100 %
b10100 $
b10100 #
b1010 "
b1010 !
$end
#100
b11110 !
b11110 ,
b11110 "
b11110 '
#200
b10100 !
b10100 ,
b110010 %
b110010 *
b101000 $
b101000 )
b1010 #
b1010 (
b10100 "
b10100 '
#300
b1010 !
b1010 ,
b1 &
b1 +
#500
b110010 !
b110010 ,
b110010 $
b110010 )
b10 &
b10 +
#600
b10100 !
b10100 ,
b0 %
b0 *
b10100 $
b10100 )
b0 #
b0 (
b0 "
b0 '
#700
b0 !
b0 ,
b11 &
b11 +
#800
b110010 !
b110010 ,
b110010 %
b110010 *
#900
b101000 $
b101000 )
b1010 #
b1010 (
b10100 "
b10100 '
