RAM.sv
module RAM (input logic write_EN,
            input logic read_rddisEN,
            input logic [15:0] read_address,
            input logic [15:0] write_address,
            input logic [15:0] write_value,
            output logic [15:0] word);
            logic [9:0] reduced_read_address;
            logic [9:0] reduced_write_address;
logic [15:0] mem [1023:0];
initial begin
  $readmemb("RAM_input.txt", mem);
end
always @ (read_address or write_address or write_value or write_EN or read_rddisEN) begin
  if (read_rddisEN == 0) begin
    reduced_read_address = read_address[9:0];
    reduced_write_address = write_address[9:0];
  end
  if (write_EN)
    mem[reduced_write_address] = write_value;
  word <= mem[reduced_read_address];
end
endmodule

RAM_tb.sv
timeunit 10ps/1ps;
module test ();
            logic write_EN;
            logic read_rddisEN;
            logic [15:0] read_address;
            logic [15:0] write_address;
            logic [15:0] write_value;
            logic [15:0] word;
            RAM us(.*);
      initial begin
            $dumpfile("RAM.vcd");
            $dumpvars;
      end
    initial begin
      #10;
      read_rddisEN = 0;
      read_address = 16'd0;
      #10;
      //write_EN = 1'b0;
      read_address = 16'd0;
      //write_address = 16'd1;
      //write_value = 16'd0;
      #10;
      write_EN = 1'b1;
      write_value = 16'd00;
      #10;
      write_address = 16'd1;
      write_value = 16'd10;
      #10;
      write_address = 16'd2;
      write_value = 16'd20;
      #10;
      read_address = 16'd1;
      #10;
      read_address = 16'd2;
      read_rddisEN = 1;
      #10;
      read_address = 16'd3;
      #10;
      read_rddisEN = 0;
      write_EN = 1'b0;
      write_value = 16'd1000;
      #10;
      read_address = 16'd2;
      #10;
      read_address = 16'd1024;
      write_address = 16'd1024;
      #10;
      write_EN = 1'b1;
      #10;
      #10;

    $finish();
    end
endmodule

RAM.vcd
$date
	Fri Jun  8 22:43:31 2018
$end
$version
	Icarus Verilog
$end
$timescale
	1ps
$end
$scope module test $end
$var wire 16 ! word [15:0] $end
$var reg 16 " read_address [15:0] $end
$var reg 1 # read_rddisEN $end
$var reg 1 $ write_EN $end
$var reg 16 % write_address [15:0] $end
$var reg 16 & write_value [15:0] $end
$scope module us $end
$var wire 16 ' read_address [15:0] $end
$var wire 1 # read_rddisEN $end
$var wire 1 $ write_EN $end
$var wire 16 ( write_address [15:0] $end
$var wire 16 ) write_value [15:0] $end
$var reg 10 * reduced_read_address [9:0] $end
$var reg 10 + reduced_write_address [9:0] $end
$var reg 16 , word [15:0] $end
$upscope $end
$upscope $end
$enddefinitions $end
#0
$dumpvars
bx ,
bx +
bx *
bx )
bx (
bx '
bx &
bx %
x$
x#
bx "
bx !
$end
#100
b1010000000001111 !
b1010000000001111 ,
b0 *
b0 "
b0 '
0#
#300
b0 &
b0 )
1$
#400
b1 +
b1010 &
b1010 )
b1 %
b1 (
#500
b10 +
b10100 &
b10100 )
b10 %
b10 (
#600
b1010 !
b1010 ,
b1 *
b1 "
b1 '
#700
1#
b10 "
b10 '
#800
b11 "
b11 '
#900
b1010000000001111 !
b1010000000001111 ,
b11 *
b1111101000 &
b1111101000 )
0$
0#
#1000
b10100 !
b10100 ,
b10 *
b10 "
b10 '
#1100
b1010000000001111 !
b1010000000001111 ,
b0 +
b0 *
b10000000000 %
b10000000000 (
b10000000000 "
b10000000000 '
#1200
b1111101000 !
b1111101000 ,
1$
