RAM.sv
module RAM (input logic write_EN,
            input logic [15:0] read_address,
            input logic [15:0] write_address,
            input logic [15:0] write_value,
            output logic [15:0] word);
logic [15:0] mem [1023:0];
always @ (read_address or write_address or write_EN or write_value)
  begin
  if (write_EN)
    mem[write_address] = write_value;
  word = mem[read_address];
  end
endmodule

RAM_tb.sv
timeunit 10ps/1ps;
module test ();
            logic write_EN;
            logic [15:0] read_address;
            logic [15:0] write_address;
            logic [15:0] write_value;
            logic [15:0] word;
            RAM us(.*);
      initial begin
            $dumpfile("RAM.vcd");
            $dumpvars;
      end
    initial begin
      write_EN = 1'b0;
      read_address = 16'd0;
      write_address = 16'd0;
      write_value = 16'd0;
      #10
      write_EN = 1'b1;
      write_value = 16'd00;
      #10
      write_address = 16'd1;
      write_value = 16'd10;
      #10
      write_address = 16'd2;
      write_value = 16'd20;
      #10
      read_address = 16'd1;
      #10
      read_address = 16'd2;
      #10
      read_address = 16'd3;
      #10
      write_EN = 1'b0;
      write_value = 16'd1000;
      #10
      read_address = 16'd2;
      #10
      read_address = 16'd1;
      write_address = 16'd1;
      #10
      write_EN = 1'b1;
      #10
      #10

    $finish();
    end

endmodule

RAM.vcd
$date
	Tue Jun  5 00:23:37 2018
$end
$version
	Icarus Verilog
$end
$timescale
	1ps
$end
$scope module test $end
$var wire 16 ! word [15:0] $end
$var reg 16 " read_address [15:0] $end
$var reg 1 # write_EN $end
$var reg 16 $ write_address [15:0] $end
$var reg 16 % write_value [15:0] $end
$scope module us $end
$var wire 16 & read_address [15:0] $end
$var wire 1 # write_EN $end
$var wire 16 ' write_address [15:0] $end
$var wire 16 ( write_value [15:0] $end
$var reg 16 ) word [15:0] $end
$upscope $end
$upscope $end
$enddefinitions $end
#0
$dumpvars
bx )
b0 (
b0 '
b0 &
b0 %
b0 $
0#
b0 "
bx !
$end
#100
b0 !
b0 )
1#
#200
b1010 %
b1010 (
b1 $
b1 '
#300
b10100 %
b10100 (
b10 $
b10 '
#400
b1010 !
b1010 )
b1 "
b1 &
#500
b10100 !
b10100 )
b10 "
b10 &
#600
bx !
bx )
b11 "
b11 &
#700
b1111101000 %
b1111101000 (
0#
#800
b10100 !
b10100 )
b10 "
b10 &
#900
b1010 !
b1010 )
b1 $
b1 '
b1 "
b1 &
#1000
b1111101000 !
b1111101000 )
1#
