register_bank.sv
module register_bank (
  input logic clk,
  input logic reset,
  input logic read_1EN,
  input logic read_2EN,
  input logic writeEN,
  input logic [4:0] read_1,
  input logic [4:0] read_2,
  input logic [4:0] write_reg_address,
  input logic [15:0] write_val,
  output logic [15:0] line_a,
  output logic [15:0] line_b);

reg [15:0] registerfile [0:15];

always @ (posedge clk or negedge reset) begin
  if (read_1EN)
    line_a <= registerfile[read_1];
  if (read_2EN)
    line_b <= registerfile[read_2];
  if (writeEN)
    registerfile[write_reg_address] <= write_val;
  if (!reset)
    begin
    registerfile[0] <= 16'b0;
    registerfile[1] <= 16'b0;
    /*reg [1] stores the mem offset*/
    registerfile[2] <= 16'b0;
    registerfile[3] <= 16'b0;
    registerfile[4] <= 16'b0;
    registerfile[5] <= 16'b0;
    registerfile[6] <= 16'b0;
    registerfile[7] <= 16'b0;
    registerfile[8] <= 16'b0;
    registerfile[9] <= 16'b0;
    registerfile[10] <= 16'b0;
    registerfile[11] <= 16'b0;
    registerfile[12] <= 16'b0;
    registerfile[13] <= 16'b0;
    registerfile[14] <= 16'b0;
    registerfile[15] <= 16'b0;
    end
end
endmodule

register_bank_tb.sv
timeunit 10ps/1ps;
module test_reg_bank ();
  logic clk;
  logic reset;
  logic read_1EN;
  logic read_2EN;
  logic writeEN;
  logic [4:0] read_1;
  logic [4:0] read_2;
  logic [4:0] write_reg_address;
  logic [15:0] write_val;
  logic [15:0] line_a;
  logic [15:0] line_b;
      register_bank u1(.*);
  initial begin
        $dumpfile("register_bank.vcd");
        $dumpvars;
        clk = 0;
        reset = 1;
        read_1EN = 1;
        read_2EN = 1;
        writeEN = 0;
        read_1 = 16'd3;
        read_2 = 16'd4;
        write_reg_address = 5'd15;
        write_val = 16'd10;
        end
  always
  #5 clk = !clk;

  initial begin
  #10;
  reset = 0;
  #10;
  reset = 1;
  read_1 = 5'd15;
  #10;
  writeEN = 1;
  write_val = 16'd20;
  #10;
  write_reg_address = 16'd4;
  write_val = 16'd10;
  #10;
  reset = 0;
  #10;
  reset = 1;
  #10;
  $finish();
  end
endmodule

register_bank.vcd
$date
	Tue Jun  5 17:09:31 2018
$end
$version
	Icarus Verilog
$end
$timescale
	1ps
$end
$scope module test_reg_bank $end
$var wire 16 ! line_b [15:0] $end
$var wire 16 " line_a [15:0] $end
$var reg 1 # clk $end
$var reg 5 $ read_1 [4:0] $end
$var reg 1 % read_1EN $end
$var reg 5 & read_2 [4:0] $end
$var reg 1 ' read_2EN $end
$var reg 1 ( reset $end
$var reg 1 ) writeEN $end
$var reg 5 * write_reg_address [4:0] $end
$var reg 16 + write_val [15:0] $end
$scope module u1 $end
$var wire 1 # clk $end
$var wire 5 , read_1 [4:0] $end
$var wire 1 % read_1EN $end
$var wire 5 - read_2 [4:0] $end
$var wire 1 ' read_2EN $end
$var wire 1 ( reset $end
$var wire 1 ) writeEN $end
$var wire 5 . write_reg_address [4:0] $end
$var wire 16 / write_val [15:0] $end
$var reg 16 0 line_a [15:0] $end
$var reg 16 1 line_b [15:0] $end
$upscope $end
$upscope $end
$enddefinitions $end
#0
$dumpvars
bx 1
bx 0
b1010 /
b1111 .
b100 -
b11 ,
b1010 +
b1111 *
0)
1(
1'
b100 &
1%
b11 $
0#
bx "
bx !
$end
#50
1#
#100
0#
0(
#150
b0 !
b0 1
b0 "
b0 0
1#
#200
0#
b1111 $
b1111 ,
1(
#250
1#
#300
0#
b10100 +
b10100 /
1)
#350
1#
#400
0#
b1010 +
b1010 /
b100 *
b100 .
#450
b10100 "
b10100 0
1#
#500
b1010 !
b1010 1
0#
0(
#550
b0 !
b0 1
b0 "
b0 0
1#
#600
0#
1(
