register.sv
module register (input logic enable,
                input logic clock,
                input logic reset,
                input logic [15:0] write_word,
                output logic [15:0] readword);

always @ (posedge clock or negedge reset) begin
  if (enable)
    readword <= write_word;
  if (~reset)
    readword <= 16'b0;
end
endmodule

register_tb.sv
timeunit 10ps/1ps;
module test_reg ();
                logic enable;
                logic clock;
                logic reset;
                logic [15:0] write_word;
                logic  [15:0] readword;
      register u1(.*);
    initial begin
          $dumpfile("register.vcd");
          $dumpvars;
    clock = 0;
    reset = 2'b1;
    enable = 2'b0;
    write_word = 10'd20;

    end
  always
  #10  clock = !clock;

  initial begin
  #10;
  reset = 2'b0;
  #10;
  reset = 2'b1;
  #10;
  write_word = 10'd20;
  enable = 2'b1;
  #10;
  reset = 2'b0;
  #10;
  reset = 2'b1;
  #10;
  enable = 0;
  write_word = 10'd10;
  #10;
  enable = 1;
  write_word = 10'd30;
  #10;
  $finish();
  end
endmodule

register.vcd
$date
	Fri Jun  8 18:57:22 2018
$end
$version
	Icarus Verilog
$end
$timescale
	1ps
$end
$scope module test_reg $end
$var wire 16 ! readword [15:0] $end
$var reg 1 " clock $end
$var reg 1 # enable $end
$var reg 1 $ reset $end
$var reg 16 % write_word [15:0] $end
$scope module u1 $end
$var wire 1 " clock $end
$var wire 1 # enable $end
$var wire 1 $ reset $end
$var wire 16 & write_word [15:0] $end
$var reg 16 ' readword [15:0] $end
$upscope $end
$upscope $end
$enddefinitions $end
#0
$dumpvars
bx '
b10100 &
b10100 %
1$
0#
0"
bx !
$end
#100
b0 !
b0 '
0$
1"
#200
1$
0"
#300
b10100 !
b10100 '
1#
1"
#400
b0 !
b0 '
0$
0"
#500
b10100 !
b10100 '
1$
1"
#600
b1010 %
b1010 &
0#
0"
#700
b11110 !
b11110 '
b11110 %
b11110 &
1#
1"
