state_machine.sv
module state_machine(
  input logic clk,
  input logic state_reset,
  output logic [1:0] state);
  logic [1:0] next_state;
  always @ (posedge clk or negedge state_reset) begin
    if (~state_reset)
      next_state <= 2'b00;
    if (clk == 1) begin
    case (next_state)
      2'b00: next_state <= 2'b01;
      2'b01: next_state <= 2'b10;
      2'b10: next_state <= 2'b11;
      2'b11: next_state <= 2'b00;
    endcase
    end
    if (clk == 1)
    state <= next_state;
  end
endmodule

state_machine_tb.sv
timeunit 10ps/1ps;
module test();
  logic clk;
  logic state_reset;
  logic [1:0] state;
  logic [1:0] next_state;
  state_machine u1(.*);

  initial begin
        $dumpfile("state_machine.vcd");
        $dumpvars;
    clk = 0;
    state_reset = 1;
  end
  always
    #5 clk = !clk;

  initial begin
  #10;
    state_reset = 0;
  #10;
    state_reset = 1;
  #40;
    state_reset = 0;
  #10;
    state_reset = 1;
  #10;

  $finish();
  end
endmodule

state_machine.vcd
$date
	Tue Jun  5 18:57:34 2018
$end
$version
	Icarus Verilog
$end
$timescale
	1ps
$end
$scope module test $end
$var wire 2 ! state [1:0] $end
$var reg 1 " clk $end
$var reg 1 # state_reset $end
$scope module u1 $end
$var wire 1 " clk $end
$var wire 1 # state_reset $end
$var reg 2 $ next_state [1:0] $end
$var reg 2 % state [1:0] $end
$upscope $end
$upscope $end
$enddefinitions $end
#0
$dumpvars
bx %
bx $
1#
0"
bx !
$end
#50
1"
#100
b0 $
0"
0#
#150
b0 !
b0 %
b1 $
1"
#200
0"
1#
#250
b1 !
b1 %
b10 $
1"
#300
0"
#350
b10 !
b10 %
b11 $
1"
#400
0"
#450
b11 !
b11 %
b0 $
1"
#500
0"
#550
b0 !
b0 %
b1 $
1"
#600
b0 $
0"
0#
#650
b1 $
1"
#700
0"
1#
#750
b1 !
b1 %
b10 $
1"
